chaos/__init__.py
chaos/allocation.py
chaos/apps.py
chaos/cloning.py
chaos/data_migrations.py
chaos/exporters.py
chaos/filters.py
chaos/models.py
chaos/receivers.py
chaos/rest.py
chaos/routers.py
chaos/scores.py
chaos/serializers.py
chaos/signals.py
chaos/urls.py
chaos/utils.py
chaos/views.py
chaos/viewsets.py
chaos/viewsets_autocomplete.py
chaos/migrations/0001_initial.py
chaos/migrations/0002_auto_20171127_0627.py
chaos/migrations/0003_auto_20180104_1742.py
chaos/migrations/0004_auto_20180112_1140.py
chaos/migrations/0005_auto_20180119_1257.py
chaos/migrations/0006_auto_20180205_0749.py
chaos/migrations/0007_auto_20180411_0927.py
chaos/migrations/__init__.py
django_chaos-3.0.2.dist-info/DESCRIPTION.rst
django_chaos-3.0.2.dist-info/METADATA
django_chaos-3.0.2.dist-info/RECORD
django_chaos-3.0.2.dist-info/WHEEL
django_chaos-3.0.2.dist-info/metadata.json
django_chaos-3.0.2.dist-info/top_level.txt
