Metadata-Version: 2.0
Name: django-chaos
Version: 3.0.2
Summary: Chaos is a project that you can use to do project management
Home-page: https://gitlab.sigmageosistemas.com.br/dev/django-chaos
Author: George Silva
Author-email: george@sigmageosistemas.com.br
License: MIT
Keywords: django-chaos
Platform: UNKNOWN
Classifier: Development Status :: 3 - Alpha
Classifier: Framework :: Django
Classifier: Framework :: Django :: 1.8
Classifier: Framework :: Django :: 1.9
Classifier: Framework :: Django :: 1.10
Classifier: Intended Audience :: Developers
Classifier: License :: OSI Approved :: BSD License
Classifier: Natural Language :: English
Classifier: Programming Language :: Python :: 2
Classifier: Programming Language :: Python :: 2.7
Classifier: Programming Language :: Python :: 3
Classifier: Programming Language :: Python :: 3.3
Classifier: Programming Language :: Python :: 3.4
Classifier: Programming Language :: Python :: 3.5
Requires-Dist: django
Requires-Dist: django-colorfield
Requires-Dist: django-common-models
Requires-Dist: django-dirtyfields
Requires-Dist: django-excel
Requires-Dist: django-file-context
Requires-Dist: django-filter
Requires-Dist: django-mptt
Requires-Dist: django-recurrence
Requires-Dist: django-taggit
Requires-Dist: django-taggit-serializer
Requires-Dist: djangorestframework
Requires-Dist: djangorestframework-filters
Requires-Dist: djangorestframework-gis
Requires-Dist: icalendar
Requires-Dist: jsonfield
Requires-Dist: pyexcel
Requires-Dist: pyexcel-io
Requires-Dist: pyexcel-webio
Requires-Dist: pyexcel-xlsx
